pyerror/__init__.py
pyerror/info.py
pyerror/templates.py
PyErrManager-2.0.dist-info/LICENSE
PyErrManager-2.0.dist-info/METADATA
PyErrManager-2.0.dist-info/WHEEL
PyErrManager-2.0.dist-info/top_level.txt
PyErrManager-2.0.dist-info/RECORD
