Metadata-Version: 2.1
Name: PyErrManager
Version: 2.0
Summary: Exception management package
Home-page: UNKNOWN
Author: Hyppoprogramm
Author-email: programm.jeremiah@yandex.ru
License: UNKNOWN
Platform: UNKNOWN
Classifier: Programming Language :: Python :: 3
Classifier: License :: OSI Approved :: MIT License
Classifier: Operating System :: OS Independent
Requires-Python: >=3.6
